{"job":4020,"level":247,"counts":{"811":{"playCount":0,"maxPlayCount":2},"806":{"playCount":0,"maxPlayCount":3},"802":{"playCount":0,"maxPlayCount":3},"150":{"playCount":0,"maxPlayCount":3},"10000":{"playCount":0,"maxPlayCount":0},"100":{"playCount":0,"maxPlayCount":3},"2":{"playCount":0,"maxPlayCount":0},"810":{"playCount":0,"maxPlayCount":2},"400":{"playCount":0,"maxPlayCount":1},"500":{"playCount":0,"maxPlayCount":4},"808":{"playCount":0,"maxPlayCount":2},"801":{"playCount":0,"maxPlayCount":3},"800":{"playCount":0,"maxPlayCount":1},"10002":{"playCount":0,"maxPlayCount":0},"803":{"playCount":0,"maxPlayCount":3},"805":{"playCount":0,"maxPlayCount":3}},"challengeDebuffTime":0,"name":"아주르레인","version":2,"time":1606142822,"money":492621,"cid":"1176954183091426"}