{"job":4010,"money":199999,"version":2,"name":"κ³¨λ“λ¬ΈνΈ","cid":"335643104248975","level":421,"counts":{"400":{"maxPlayCount":5,"playCount":0},"500":{"maxPlayCount":4,"playCount":0},"100":{"maxPlayCount":3,"playCount":3},"10000":{"maxPlayCount":0,"playCount":0},"803":{"maxPlayCount":5,"playCount":0},"10002":{"maxPlayCount":0,"playCount":0},"800":{"maxPlayCount":5,"playCount":0},"801":{"maxPlayCount":5,"playCount":0},"802":{"maxPlayCount":3,"playCount":0}},"challengeDebuffTime":0,"time":1583340012}