{"cid":"69346541978353","challengeDebuffTime":0,"version":2,"name":"이그나이","level":412,"time":1581519961,"job":1004,"money":199999,"counts":{"802":{"maxPlayCount":3,"playCount":0},"10002":{"maxPlayCount":0,"playCount":0},"100":{"maxPlayCount":3,"playCount":0},"803":{"maxPlayCount":5,"playCount":0},"1301":{"maxPlayCount":0,"playCount":2},"500":{"maxPlayCount":4,"playCount":0},"400":{"maxPlayCount":5,"playCount":0},"801":{"maxPlayCount":5,"playCount":0},"800":{"maxPlayCount":5,"playCount":0},"10000":{"maxPlayCount":0,"playCount":0}}}