{"level":423,"time":1590506041,"version":2,"name":"조시","money":199999,"job":1006,"counts":{"10000":{"playCount":0,"maxPlayCount":0},"100":{"playCount":0,"maxPlayCount":3},"801":{"playCount":0,"maxPlayCount":5},"400":{"playCount":0,"maxPlayCount":5},"803":{"playCount":0,"maxPlayCount":5},"805":{"playCount":0,"maxPlayCount":3},"800":{"playCount":0,"maxPlayCount":5},"10002":{"playCount":0,"maxPlayCount":0},"802":{"playCount":0,"maxPlayCount":3},"500":{"playCount":0,"maxPlayCount":4}},"cid":"790377061681688","challengeDebuffTime":0}